LICENSE
README.md
dynamics/__init__.py
dynamics/api_actions.py
dynamics/api_functions.py
dynamics/apply_functions.py
dynamics/cache.py
dynamics/client/__init__.py
dynamics/client/aio.py
dynamics/client/base.py
dynamics/client/sync.py
dynamics/enums.py
dynamics/exceptions.py
dynamics/fetchxml.py
dynamics/normalizers.py
dynamics/py.typed
dynamics/query_functions.py
dynamics/status.py
dynamics/test.py
dynamics/typing.py
dynamics/utils.py
dynamics_client-0.8.4.dist-info/LICENSE
dynamics_client-0.8.4.dist-info/METADATA
dynamics_client-0.8.4.dist-info/WHEEL
dynamics_client-0.8.4.dist-info/RECORD
