Metadata-Version: 2.1
Name: dynamics-client
Version: 0.8.4
Summary: Client for making Web API request from a Microsoft Dynamics 365 Database.
Home-page: https://github.com/MrThearMan/dynamics-client/
License: MIT
Keywords: Microsoft,Dynamics,client
Author: Matti Lamppu
Author-email: lamppu.matti.akseli@gmail.com
Requires-Python: >=3.9,<4
Classifier: Intended Audience :: Developers
Classifier: License :: OSI Approved :: MIT License
Classifier: Natural Language :: English
Classifier: Operating System :: OS Independent
Classifier: Programming Language :: Python
Classifier: Programming Language :: Python :: 3
Classifier: Programming Language :: Python :: 3.9
Classifier: Programming Language :: Python :: 3.10
Classifier: Programming Language :: Python :: 3.11
Classifier: Programming Language :: Python :: 3.12
Classifier: Programming Language :: Python :: 3 :: Only
Provides-Extra: django
Requires-Dist: Django (>=4.2) ; extra == "django"
Requires-Dist: aiosqlite (>=0.20.0)
Requires-Dist: authlib (>=1.3.0)
Requires-Dist: djangorestframework (>=3.12.0) ; extra == "django"
Requires-Dist: httpx (>=0.27.0)
Requires-Dist: typing-extensions (>=4.10.0) ; python_version < "3.11"
Requires-Dist: tzdata (>=2024.1)
Project-URL: Bug Tracker, https://github.com/MrThearMan/dynamics-client/issues
Project-URL: Repository, https://github.com/MrThearMan/dynamics-client/
